Metadata-Version: 1.1
Name: synpurge
Version: 4
Summary: Purges Matrix room history room using the HTTP API
Home-page: https://github.com/aperezdc/synpurge
Author: Adrian Perez de Castro
Author-email: aperez@igalia.com
License: UNKNOWN
Platform: UNKNOWN
Classifier: Development Status :: 3 - Alpha
Classifier: Environment :: Console
Classifier: Intended Audience :: System Administrators
Classifier: License :: OSI Approved :: GNU General Public License v3 (GPLv3)
Classifier: Natural Language :: English
Classifier: Operating System :: OS Independent
Classifier: Programming Language :: Python :: 3
Classifier: Programming Language :: Python :: 3 :: Only
Classifier: Programming Language :: Python :: 3.4
Classifier: Topic :: Communications :: Chat
Classifier: Topic :: Utilities
